AUTHORS.rst
CONTRIBUTING.rst
HISTORY.rst
LICENSE
MANIFEST.in
README.rst
setup.cfg
setup.py
docs/Makefile
docs/authors.rst
docs/conf.py
docs/contributing.rst
docs/history.rst
docs/index.rst
docs/installation.rst
docs/make.bat
docs/readme.rst
docs/usage.rst
sdfparser/__init__.py
sdfparser/models.py
sdfparser/parsers.py
sdfparser.egg-info/PKG-INFO
sdfparser.egg-info/SOURCES.txt
sdfparser.egg-info/dependency_links.txt
sdfparser.egg-info/not-zip-safe
sdfparser.egg-info/top_level.txt
tests/.DS_Store
tests/__init__.py
tests/test_sdfparser.py
tests/data/.DS_Store
tests/data/DRD3_Antagonists.sdf