Metadata-Version: 1.1
Name: sdfparser
Version: 0.1.0
Summary: Parser for Chemical table files are files that contain information about chemicals.
Home-page: https://github.com/llazzaro/sdfparser
Author: Leonardo Lazzaro
Author-email: llazzaro@dc.uba.ar
License: ISCL
Keywords: sdfparser
Platform: UNKNOWN
Classifier: Development Status :: 2 - Pre-Alpha
Classifier: Intended Audience :: Developers
Classifier: License :: OSI Approved :: ISC License (ISCL)
Classifier: Natural Language :: English
Classifier: Programming Language :: Python :: 2
Classifier: Programming Language :: Python :: 2.6
Classifier: Programming Language :: Python :: 2.7
Classifier: Programming Language :: Python :: 3
Classifier: Programming Language :: Python :: 3.3
Classifier: Programming Language :: Python :: 3.4
